ajtc_tools/__init__.py
ajtc_tools/images.py
ajtc_tools/searching.py
ajtc_tools/sorting.py
ajtc_tools/timing.py
ajtc_tools-0.2.0.dist-info/METADATA
ajtc_tools-0.2.0.dist-info/WHEEL
ajtc_tools-0.2.0.dist-info/top_level.txt
ajtc_tools-0.2.0.dist-info/RECORD
