Metadata-Version: 2.2
Name: ajtc_tools
Version: 0.2.0
Summary: A utility module containing a variety of code I use regularly
Author-email: Ainsworth Coultart <ainsworthcoultart@gmail.com>
License: MIT
Project-URL: Homepage, https://github.com/a-842/ajtc_tools
Requires-Python: >=3.7
Requires-Dist: pillow
